botw_tools/__init__.py
botw_tools/aamp.py
botw_tools/actorinfo.py
botw_tools/byml.py
botw_tools/common.py
botw_tools/sarc.py
botw_tools/yaz0.py
botw_tools-0.5.2.dist-info/METADATA
botw_tools-0.5.2.dist-info/WHEEL
botw_tools-0.5.2.dist-info/entry_points.txt
botw_tools-0.5.2.dist-info/top_level.txt
botw_tools-0.5.2.dist-info/RECORD
