Metadata-Version: 2.1
Name: botw-tools
Version: 0.5.2
Summary: A collection of tools for modding Breath of the Wild
Home-page: https://github.com/krenyy/botw_tools
Author: kreny
Author-email: kronerm9@gmail.com
License: UNKNOWN
Platform: UNKNOWN
Classifier: Programming Language :: Python :: 3 :: Only
Classifier: License :: OSI Approved :: GNU General Public License v3 or later (GPLv3+)
Classifier: Operating System :: OS Independent
Requires-Python: >=3.6
Requires-Dist: oead (~=1.2.1)
Requires-Dist: colorama (~=0.4.4)
